<?xml version = '1.0' encoding = 'UTF-8'?>
<FKIndexAssociation class="oracle.dbtools.crest.model.design.relational.FKIndexAssociation" directorySegmentName="seg_0" id="F484C9EF-CC91-FF34-80C0-281CA772E3A4" containerWithKeyObject="E7603F9B-A0AC-E6C4-C890-4E7CE318732A" localFKIndex="AC3C8FA7-8D54-A5AA-F8BE-A2E7F9697ABF" name="CS_D_COLL_DIARIO_DOVE_FK">
<sourceConnName>CS_SISO_ROMA</sourceConnName>
<sourceObjSchema>CS_SISO</sourceObjSchema>
<sourceObjName>CS_D_COLL_DIARIO_DOVE_FK</sourceObjName>
<createdBy>marcoultra</createdBy>
<createdTime>2015-06-03 13:57:19 UTC</createdTime>
<ownerDesignName>CS</ownerDesignName>
<importedID>A681C052-9A58-6076-953D-AA250665AD1A</importedID>
<deleteRule>NO ACTION</deleteRule>
<referredTableID>9FA5AAE6-E5FC-F0AB-CA81-0415F1F52B3A</referredTableID>
<keyObject>124555D2-8105-0E89-7883-770597F42248</keyObject>
<referredKeyID>124555D2-8105-0E89-7883-770597F42248</referredKeyID>
<mandatory>false</mandatory>
<transferable>true</transferable>
<rely>false</rely>
<columnDependencyConstraintGenerateInDDL>false</columnDependencyConstraintGenerateInDDL>
</FKIndexAssociation>